awslabs/__init__.py
awslabs/sagemaker_ai_mcp_server/README.md
awslabs/sagemaker_ai_mcp_server/__init__.py
awslabs/sagemaker_ai_mcp_server/aws_helper.py
awslabs/sagemaker_ai_mcp_server/consts.py
awslabs/sagemaker_ai_mcp_server/logging_helper.py
awslabs/sagemaker_ai_mcp_server/server.py
awslabs/sagemaker_ai_mcp_server/sagemaker_hyperpod/__init__.py
awslabs/sagemaker_ai_mcp_server/sagemaker_hyperpod/hyperpod_cluster_node_handler.py
awslabs/sagemaker_ai_mcp_server/sagemaker_hyperpod/hyperpod_stack_handler.py
awslabs/sagemaker_ai_mcp_server/sagemaker_hyperpod/models.py
awslabs_sagemaker_ai_mcp_server-1.0.5.dist-info/METADATA
awslabs_sagemaker_ai_mcp_server-1.0.5.dist-info/WHEEL
awslabs_sagemaker_ai_mcp_server-1.0.5.dist-info/entry_points.txt
awslabs_sagemaker_ai_mcp_server-1.0.5.dist-info/licenses/LICENSE
awslabs_sagemaker_ai_mcp_server-1.0.5.dist-info/licenses/NOTICE
awslabs_sagemaker_ai_mcp_server-1.0.5.dist-info/RECORD
